{"val_sharpe": -0.8868499842222312, "val_loss": -0.7660957374245909, "train_loss": -0.7660957374245909, "epoch": 0, "timestamp": 1764849848, "checkpoint_dir_name": null, "done": false, "training_iteration": 1, "trial_id": "67000927", "date": "2025-12-04_07-04-08", "time_this_iter_s": 190.23261618614197, "time_total_s": 190.23261618614197, "pid": 96993, "hostname": "Rayyans-MacBook-Pro.local", "node_ip": "127.0.0.1", "config": {"hidden_dim": 64, "num_transformer_layers": 1, "num_attention_heads": 2, "dropout": 0.18108206622836454, "lstm_num_layers": 1, "lstm_dropout": 0.19615572342402424, "learning_rate": 0.00022310798331270093, "weight_decay": 6.130175292204136e-06, "batch_size": 256, "weight_hidden_dim": 16, "weight_dropout": 0.21740282650290638, "num_epochs": 15}, "time_since_restore": 190.23261618614197, "iterations_since_restore": 1}
{"val_sharpe": -0.717325843357317, "val_loss": -0.8075925120432313, "train_loss": -0.8075925120432313, "epoch": 1, "timestamp": 1764850004, "checkpoint_dir_name": null, "done": false, "training_iteration": 2, "trial_id": "67000927", "date": "2025-12-04_07-06-44", "time_this_iter_s": 155.53701496124268, "time_total_s": 345.76963114738464, "pid": 96993, "hostname": "Rayyans-MacBook-Pro.local", "node_ip": "127.0.0.1", "config": {"hidden_dim": 64, "num_transformer_layers": 1, "num_attention_heads": 2, "dropout": 0.18108206622836454, "lstm_num_layers": 1, "lstm_dropout": 0.19615572342402424, "learning_rate": 0.00022310798331270093, "weight_decay": 6.130175292204136e-06, "batch_size": 256, "weight_hidden_dim": 16, "weight_dropout": 0.21740282650290638, "num_epochs": 15}, "time_since_restore": 345.76963114738464, "iterations_since_restore": 2}
{"val_sharpe": -0.6612698190595028, "val_loss": -0.9426951050651049, "train_loss": -0.9426951050651049, "epoch": 2, "timestamp": 1764850159, "checkpoint_dir_name": null, "done": false, "training_iteration": 3, "trial_id": "67000927", "date": "2025-12-04_07-09-19", "time_this_iter_s": 155.01796078681946, "time_total_s": 500.7875919342041, "pid": 96993, "hostname": "Rayyans-MacBook-Pro.local", "node_ip": "127.0.0.1", "config": {"hidden_dim": 64, "num_transformer_layers": 1, "num_attention_heads": 2, "dropout": 0.18108206622836454, "lstm_num_layers": 1, "lstm_dropout": 0.19615572342402424, "learning_rate": 0.00022310798331270093, "weight_decay": 6.130175292204136e-06, "batch_size": 256, "weight_hidden_dim": 16, "weight_dropout": 0.21740282650290638, "num_epochs": 15}, "time_since_restore": 500.7875919342041, "iterations_since_restore": 3}
{"val_sharpe": -0.873820346026871, "val_loss": -0.9106421952783571, "train_loss": -0.9106421952783571, "epoch": 3, "timestamp": 1764850328, "checkpoint_dir_name": null, "done": false, "training_iteration": 4, "trial_id": "67000927", "date": "2025-12-04_07-12-08", "time_this_iter_s": 168.99875688552856, "time_total_s": 669.7863488197327, "pid": 96993, "hostname": "Rayyans-MacBook-Pro.local", "node_ip": "127.0.0.1", "config": {"hidden_dim": 64, "num_transformer_layers": 1, "num_attention_heads": 2, "dropout": 0.18108206622836454, "lstm_num_layers": 1, "lstm_dropout": 0.19615572342402424, "learning_rate": 0.00022310798331270093, "weight_decay": 6.130175292204136e-06, "batch_size": 256, "weight_hidden_dim": 16, "weight_dropout": 0.21740282650290638, "num_epochs": 15}, "time_since_restore": 669.7863488197327, "iterations_since_restore": 4}
{"val_sharpe": -0.944818105643735, "val_loss": -1.0393449140122397, "train_loss": -1.0393449140122397, "epoch": 4, "timestamp": 1764850498, "checkpoint_dir_name": null, "done": true, "training_iteration": 5, "trial_id": "67000927", "date": "2025-12-04_07-14-58", "time_this_iter_s": 170.05488991737366, "time_total_s": 839.8412387371063, "pid": 96993, "hostname": "Rayyans-MacBook-Pro.local", "node_ip": "127.0.0.1", "config": {"hidden_dim": 64, "num_transformer_layers": 1, "num_attention_heads": 2, "dropout": 0.18108206622836454, "lstm_num_layers": 1, "lstm_dropout": 0.19615572342402424, "learning_rate": 0.00022310798331270093, "weight_decay": 6.130175292204136e-06, "batch_size": 256, "weight_hidden_dim": 16, "weight_dropout": 0.21740282650290638, "num_epochs": 15}, "time_since_restore": 839.8412387371063, "iterations_since_restore": 5}
